flame/__init__.py
flame/keyword.py
flame/loss.py
flame/version.py
flame/cli/__init__.py
flame/cli/cli.py
flame/cli/init.py
flame/cli/run.py
flame/engine/__init__.py
flame/engine/engine.py
flame/engine/evaluator.py
flame/engine/trainer.py
flame/engine/utils.py
flame/handlers/__init__.py
flame/handlers/checkpoint.py
flame/handlers/early_stopping.py
flame/handlers/handler.py
flame/handlers/metrics.py
flame/handlers/progressbar.py
flame/handlers/tensorboard.py
flame/template/run.py-tpl
flame/template/configs/test.yml-tpl
flame/template/configs/test_ddp.yml-tpl
flame/template/configs/train.yml-tpl
flame/template/configs/train_ddp.yml-tpl
pytorch_flame-0.1.2.dist-info/LICENSE
pytorch_flame-0.1.2.dist-info/METADATA
pytorch_flame-0.1.2.dist-info/WHEEL
pytorch_flame-0.1.2.dist-info/entry_points.txt
pytorch_flame-0.1.2.dist-info/top_level.txt
pytorch_flame-0.1.2.dist-info/RECORD
