Metadata-Version: 2.1
Name: pytorch-flame
Version: 0.1.2
Summary: A library based on Ignite to help you train and evaluate PyTorch neural networks more easily.
Author: Trong Le Huu
Author-email: tronglh.241@gmail.com
License: MIT License
Classifier: Intended Audience :: Developers
Classifier: License :: OSI Approved :: MIT License
Classifier: Programming Language :: Python :: 3
License-File: LICENSE
Requires-Dist: torch
Requires-Dist: pytorch-ignite
Requires-Dist: yacs
Requires-Dist: tqdm
Requires-Dist: tensorboard
